pympostor/__init__.py
pympostor/base.py
pympostor/cli.py
pympostor/config.py
pympostor/game.py
pympostor/programs.py
pympostor/words.py
pympostor-0.1.0.dist-info/METADATA
pympostor-0.1.0.dist-info/WHEEL
pympostor-0.1.0.dist-info/entry_points.txt
pympostor-0.1.0.dist-info/RECORD
