Metadata-Version: 2.4
Name: pympostor
Version: 0.1.0
Summary: CLI impostor game with AI
Author-email: Facundo Goiriz <facundogoiriz@gmail.com>
Requires-Python: >=3.13
Requires-Dist: dspy>=3.1.0
Requires-Dist: python-dotenv>=1.2.1
Requires-Dist: readchar>=4.2.1
Requires-Dist: rich>=14.2.0
Requires-Dist: typer>=0.21.1
